cf_taskpool.py
cf_taskpool-0.2.0.dist-info/licenses/LICENSE
cf_taskpool-0.2.0.dist-info/METADATA
cf_taskpool-0.2.0.dist-info/WHEEL
cf_taskpool-0.2.0.dist-info/top_level.txt
cf_taskpool-0.2.0.dist-info/RECORD
