Metadata-Version: 2.4
Name: cf-taskpool
Version: 0.2.0
Summary: A concurrent.futures-like API for executing coroutines using a pool of tasks
Author-email: George Sakkis <george.sakkis@gmail.com>
License: MIT
Project-URL: Repository, https://github.com/gsakkis/cf-taskpool
Project-URL: Issues, https://github.com/gsakkis/cf-taskpool/issues
Keywords: asyncio,concurrent,executor,task-pool,async
Classifier: Development Status :: 4 - Beta
Classifier: Intended Audience :: Developers
Classifier: License :: OSI Approved :: MIT License
Classifier: Programming Language :: Python :: 3
Classifier: Programming Language :: Python :: 3.11
Classifier: Programming Language :: Python :: 3.12
Classifier: Programming Language :: Python :: 3.13
Classifier: Topic :: Software Development :: Libraries :: Python Modules
Classifier: Framework :: AsyncIO
Requires-Python: >=3.11
License-File: LICENSE
Provides-Extra: test
Requires-Dist: pytest; extra == "test"
Requires-Dist: pytest-asyncio; extra == "test"
Requires-Dist: pytest-cov; extra == "test"
Dynamic: license-file
